route53_transfer/__init__.py
route53_transfer/app.py
route53_transfer/change_batch.py
route53_transfer/hashable_model.py
route53_transfer/models.py
route53_transfer/serialization.py
route53_transfer_ng-1.0.6.data/scripts/route53-transfer-ng
route53_transfer_ng-1.0.6.dist-info/LICENSE
route53_transfer_ng-1.0.6.dist-info/METADATA
route53_transfer_ng-1.0.6.dist-info/WHEEL
route53_transfer_ng-1.0.6.dist-info/top_level.txt
route53_transfer_ng-1.0.6.dist-info/RECORD
