Metadata-Version: 2.1
Name: route53-transfer-ng
Version: 1.0.6
Summary: Backup and restore Route53 zones, or transfer between AWS accounts.
Home-page: http://github.com/cosimo/route53-transfer-ng
Author: Cosimo Streppone
Author-email: cosimo@cpan.org
License: Apache License 2.0
Classifier: Development Status :: 4 - Beta
Classifier: Environment :: Console
Classifier: License :: OSI Approved :: MIT License
Classifier: Topic :: Utilities
Classifier: Operating System :: OS Independent
Requires-Python: >=3.6
License-File: LICENSE
Requires-Dist: pyyaml >=5.4.1
Requires-Dist: boto3
Requires-Dist: pydantic ~=2.9.2
Requires-Dist: docopt >=0.5.0
